promenade/__init__.py
promenade/__main__.py
promenade/cli.py
promenade/config.py
promenade/health.py
promenade/logs.py
promenade/server.py
promenade/static.py
promenade/supervisor.py
promenade/api/__init__.py
promenade/api/routes.py
promenade/api/websocket.py
promenade/ui/static/favicon.svg
promenade/ui/static/index.html
promenade/ui/static/assets/index-BEZVOWKr.js
promenade/ui/static/assets/index-C2vB0FrD.css
promenade-0.1.0.dist-info/METADATA
promenade-0.1.0.dist-info/WHEEL
promenade-0.1.0.dist-info/entry_points.txt
promenade-0.1.0.dist-info/licenses/LICENSE
promenade-0.1.0.dist-info/RECORD
